<?xml version="1.0" encoding="utf-8"?>
<w:document xmlns:w="http://schemas.openxmlformats.org/wordprocessingml/2006/main"
            xmlns:m="http://schemas.openxmlformats.org/officeDocument/2006/math"
            xmlns:r="http://schemas.openxmlformats.org/officeDocument/2006/relationships"
            xmlns:o="urn:schemas-microsoft-com:office:office" xmlns:v="urn:schemas-microsoft-com:vml"
            xmlns:w10="urn:schemas-microsoft-com:office:word"
            xmlns:a="http://schemas.openxmlformats.org/drawingml/2006/main"
            xmlns:pic="http://schemas.openxmlformats.org/drawingml/2006/picture"
            xmlns:wp="http://schemas.openxmlformats.org/drawingml/2006/wordprocessingDrawing">
  <w:body>

    <w:p>
      <w:pPr>
        <w:pStyle w:val="mewb-stem"/>
      </w:pPr>
      <w:r>
        <w:t xml:space="preserve">If the compressor assembly was operated as shown in figure #5 of illustration GS-0159, which bearing wear pattern would most likely develop for the motor pulley bearing shown in illustration GS-0174?</w:t>
      </w:r>
      <w:r>
        <w:t xml:space="preserve"> </w:t>
      </w:r>
      <w:r>
        <w:rPr>
          <w:i/>
        </w:rPr>
        <w:t xml:space="preserve">See illustration</w:t>
      </w:r>
      <w:r>
        <w:rPr>
          <w:i/>
        </w:rPr>
        <w:t xml:space="preserve"> </w:t>
      </w:r>

      <w:r>
        <w:rPr>
          <w:rStyle w:val="Link"/>
          <w:i/>
        </w:rPr>
        <w:t xml:space="preserve">GS-0159</w:t>
      </w:r>

      <w:r>
        <w:rPr>
          <w:i/>
        </w:rPr>
        <w:t xml:space="preserve">.</w:t>
      </w:r>
      <w:r>
        <w:t xml:space="preserve"> </w:t>
      </w:r>
      <w:r>
        <w:rPr>
          <w:i/>
        </w:rPr>
        <w:t xml:space="preserve">See illustration</w:t>
      </w:r>
      <w:r>
        <w:rPr>
          <w:i/>
        </w:rPr>
        <w:t xml:space="preserve"> </w:t>
      </w:r>

      <w:r>
        <w:rPr>
          <w:rStyle w:val="Link"/>
          <w:i/>
        </w:rPr>
        <w:t xml:space="preserve">GS-0174</w:t>
      </w:r>

      <w:r>
        <w:rPr>
          <w:i/>
        </w:rPr>
        <w:t xml:space="preserve">.</w:t>
      </w:r>
    </w:p>
    <w:p>
      <w:pPr>
        <w:pStyle w:val="mewb-abcd"/>
      </w:pPr>
      <w:r>
        <w:t xml:space="preserve">( a )</w:t>
      </w:r>
    </w:p>
    <w:p>
      <w:pPr>
        <w:pStyle w:val="mewb-abcd"/>
      </w:pPr>
      <w:r>
        <w:t xml:space="preserve">( b )</w:t>
      </w:r>
    </w:p>
    <w:p>
      <w:pPr>
        <w:pStyle w:val="mewb-abcd"/>
      </w:pPr>
      <w:r>
        <w:t xml:space="preserve">( c )</w:t>
      </w:r>
    </w:p>
    <w:p>
      <w:pPr>
        <w:pStyle w:val="mewb-abcd"/>
        <w:keepNext w:val="0"/>
      </w:pPr>
      <w:r>
        <w:t xml:space="preserve">( d )</w:t>
      </w:r>
    </w:p>

  </w:body>
</w:document>